LICENSE
MANIFEST.in
setup.cfg
setup.py
pymustache/__init__.py
pymustache/mustache.py
pymustache.egg-info/PKG-INFO
pymustache.egg-info/SOURCES.txt
pymustache.egg-info/dependency_links.txt
pymustache.egg-info/not-zip-safe
pymustache.egg-info/top_level.txt