Metadata-Version: 1.1
Name: pymustache
Version: 0.3
Summary: Mustache template engine in python
Home-page: https://github.com/lotabout/pymustache
Author: Mark Wallace
Author-email: lotabout@gmail.com
License: MIT
Download-URL: https://github.com/lotabout/pymustache/archive/v0.3.tar.gz
Keywords: mustache,template engine
Platform: UNKNOWN
